LICENSE
MANIFEST.in
NOTICE
README.rst
VERSION
setup.cfg
setup.py
src/sagemaker_pytorch_container/__init__.py
src/sagemaker_pytorch_container/training.py
src/sagemaker_pytorch_training.egg-info/PKG-INFO
src/sagemaker_pytorch_training.egg-info/SOURCES.txt
src/sagemaker_pytorch_training.egg-info/dependency_links.txt
src/sagemaker_pytorch_training.egg-info/requires.txt
src/sagemaker_pytorch_training.egg-info/top_level.txt